travertino/__init__.py
travertino/colors.py
travertino/constants.py
travertino/declaration.py
travertino/fonts.py
travertino/layout.py
travertino/node.py
travertino/size.py
travertino-0.3.0.dist-info/LICENSE
travertino-0.3.0.dist-info/METADATA
travertino-0.3.0.dist-info/WHEEL
travertino-0.3.0.dist-info/top_level.txt
travertino-0.3.0.dist-info/RECORD
