Metadata-Version: 2.1
Name: travertino
Version: 0.3.0
Summary: Travertino is a set of constants and utilities for describing user interfaces
Author: Russell Keith-Magee
Author-email: russell@keith-magee.com
License: New BSD
Project-URL: Funding, https://beeware.org/contributing/membership/
Project-URL: Tracker, https://github.com/beeware/travertino/issues
Project-URL: Source, https://github.com/beeware/travertino
Classifier: Development Status :: 3 - Alpha
Classifier: Intended Audience :: Developers
Classifier: License :: OSI Approved :: BSD License
Classifier: Operating System :: OS Independent
Classifier: Programming Language :: Python :: 3
Classifier: Programming Language :: Python :: 3.8
Classifier: Programming Language :: Python :: 3.9
Classifier: Programming Language :: Python :: 3.10
Classifier: Programming Language :: Python :: 3.11
Classifier: Programming Language :: Python :: 3.12
Classifier: Programming Language :: Python :: 3 :: Only
Classifier: Topic :: Software Development
Classifier: Topic :: Software Development :: User Interfaces
Requires-Python: >=3.8
Provides-Extra: dev
License-File: LICENSE
